{"nodes": [{"id": "src_lib_dsar_export_ts", "label": "export.ts", "file_type": "code", "source_file": "src/lib/dsar/export.ts", "source_location": "L1"}, {"id": "export_subjectnotfounderror", "label": "SubjectNotFoundError", "file_type": "code", "source_file": "src/lib/dsar/export.ts", "source_location": "L8"}, {"id": "export_subjectnotfounderror_constructor", "label": ".constructor()", "file_type": "code", "source_file": "src/lib/dsar/export.ts", "source_location": "L9"}, {"id": "export_invalidsubjecttypeerror", "label": "InvalidSubjectTypeError", "file_type": "code", "source_file": "src/lib/dsar/export.ts", "source_location": "L15"}, {"id": "export_invalidsubjecttypeerror_constructor", "label": ".constructor()", "file_type": "code", "source_file": "src/lib/dsar/export.ts", "source_location": "L16"}, {"id": "export_subjectdelegate", "label": "subjectDelegate()", "file_type": "code", "source_file": "src/lib/dsar/export.ts", "source_location": "L33"}, {"id": "export_buildsubjectexport", "label": "buildSubjectExport()", "file_type": "code", "source_file": "src/lib/dsar/export.ts", "source_location": "L40"}], "edges": [{"source": "src_lib_dsar_export_ts", "target": "client", "relation": "imports_from", "confidence": "EXTRACTED", "source_file": "src/lib/dsar/export.ts", "source_location": "L1", "weight": 1.0}, {"source": "src_lib_dsar_export_ts", "target": "pii", "relation": "imports_from", "confidence": "EXTRACTED", "source_file": "src/lib/dsar/export.ts", "source_location": "L2", "weight": 1.0}, {"source": "src_lib_dsar_export_ts", "target": "export_subjectnotfounderror", "relation": "contains", "confidence": "EXTRACTED", "source_file": "src/lib/dsar/export.ts", "source_location": "L8", "weight": 1.0}, {"source": "export_subjectnotfounderror", "target": "export_subjectnotfounderror_constructor", "relation": "method", "confidence": "EXTRACTED", "source_file": "src/lib/dsar/export.ts", "source_location": "L9", "weight": 1.0}, {"source": "src_lib_dsar_export_ts", "target": "export_invalidsubjecttypeerror", "relation": "contains", "confidence": "EXTRACTED", "source_file": "src/lib/dsar/export.ts", "source_location": "L15", "weight": 1.0}, {"source": "export_invalidsubjecttypeerror", "target": "export_invalidsubjecttypeerror_constructor", "relation": "method", "confidence": "EXTRACTED", "source_file": "src/lib/dsar/export.ts", "source_location": "L16", "weight": 1.0}, {"source": "src_lib_dsar_export_ts", "target": "export_subjectdelegate", "relation": "contains", "confidence": "EXTRACTED", "source_file": "src/lib/dsar/export.ts", "source_location": "L33", "weight": 1.0}, {"source": "src_lib_dsar_export_ts", "target": "export_buildsubjectexport", "relation": "contains", "confidence": "EXTRACTED", "source_file": "src/lib/dsar/export.ts", "source_location": "L40", "weight": 1.0}, {"source": "export_buildsubjectexport", "target": "export_subjectdelegate", "relation": "calls", "confidence": "EXTRACTED", "source_file": "src/lib/dsar/export.ts", "source_location": "L47", "weight": 1.0}], "raw_calls": [{"caller_nid": "export_subjectnotfounderror_constructor", "callee": "super", "source_file": "src/lib/dsar/export.ts", "source_location": "L10"}, {"caller_nid": "export_invalidsubjecttypeerror_constructor", "callee": "super", "source_file": "src/lib/dsar/export.ts", "source_location": "L17"}, {"caller_nid": "export_buildsubjectexport", "callee": "includes", "source_file": "src/lib/dsar/export.ts", "source_location": "L45"}, {"caller_nid": "export_buildsubjectexport", "callee": "findUnique", "source_file": "src/lib/dsar/export.ts", "source_location": "L48"}, {"caller_nid": "export_buildsubjectexport", "callee": "findMany", "source_file": "src/lib/dsar/export.ts", "source_location": "L55"}, {"caller_nid": "export_buildsubjectexport", "callee": "stripPii", "source_file": "src/lib/dsar/export.ts", "source_location": "L59"}, {"caller_nid": "export_buildsubjectexport", "callee": "all", "source_file": "src/lib/dsar/export.ts", "source_location": "L66"}, {"caller_nid": "export_buildsubjectexport", "callee": "findMany", "source_file": "src/lib/dsar/export.ts", "source_location": "L67"}, {"caller_nid": "export_buildsubjectexport", "callee": "findMany", "source_file": "src/lib/dsar/export.ts", "source_location": "L71"}, {"caller_nid": "export_buildsubjectexport", "callee": "findMany", "source_file": "src/lib/dsar/export.ts", "source_location": "L75"}, {"caller_nid": "export_buildsubjectexport", "callee": "findMany", "source_file": "src/lib/dsar/export.ts", "source_location": "L79"}]}